LICENSE
MANIFEST.in
README.md
setup.cfg
setup.py
py3winrm.egg-info/PKG-INFO
py3winrm.egg-info/SOURCES.txt
py3winrm.egg-info/dependency_links.txt
py3winrm.egg-info/requires.txt
py3winrm.egg-info/top_level.txt
winrm/__init__.py
winrm/encryption.py
winrm/exceptions.py
winrm/protocol.py
winrm/transport.py
winrm/tests/__init__.py
winrm/tests/conftest.py
winrm/tests/sample_script.ps1
winrm/tests/test_cmd.py
winrm/tests/test_encryption.py
winrm/tests/test_integration_protocol.py
winrm/tests/test_integration_session.py
winrm/tests/test_nori_type_casting.py
winrm/tests/test_powershell.py
winrm/tests/test_protocol.py
winrm/tests/test_session.py
winrm/tests/test_transport.py
winrm/tests/test_wql.py