Metadata-Version: 2.1
Name: py3winrm
Version: 0.0.1
Summary: Python library for Windows Remote Management
Home-page: https://github.com/RedHatQE/py3winrm/
Author: Alexey Diyan
Author-email: alexey.diyan@gmail.com
License: MIT license
Keywords: winrm,ws-man,devops,ws-management
Platform: UNKNOWN
Classifier: Development Status :: 4 - Beta
Classifier: Environment :: Console
Classifier: Intended Audience :: Developers
Classifier: Intended Audience :: System Administrators
Classifier: Natural Language :: English
Classifier: License :: OSI Approved :: MIT License
Classifier: Programming Language :: Python
Classifier: Programming Language :: Python :: 2
Classifier: Programming Language :: Python :: 2.7
Classifier: Programming Language :: Python :: 3
Classifier: Programming Language :: Python :: 3.6
Classifier: Programming Language :: Python :: 3.7
Classifier: Programming Language :: Python :: Implementation :: PyPy
Classifier: Topic :: Software Development :: Libraries :: Python Modules
Classifier: Topic :: System :: Clustering
Classifier: Topic :: System :: Distributed Computing
Classifier: Topic :: System :: Systems Administration
Provides-Extra: kerberos
Provides-Extra: credssp
